cs3client/__init__.py
cs3client/app.py
cs3client/auth.py
cs3client/checkpoint.py
cs3client/config.py
cs3client/cs3client.py
cs3client/cs3resource.py
cs3client/file.py
cs3client/group.py
cs3client/share.py
cs3client/statuscodehandler.py
cs3client/user.py
cs3client/exceptions/__init__.py
cs3client-1.6.0.dist-info/licenses/LICENSE
cs3client-1.6.0.dist-info/METADATA
cs3client-1.6.0.dist-info/WHEEL
cs3client-1.6.0.dist-info/top_level.txt
cs3client-1.6.0.dist-info/RECORD
