Metadata-Version: 2.4
Name: cs3client
Version: 1.6.0
Summary: CS3 client for Python
Home-page: https://github.com/cs3org/cs3-python-client
Author: Rasmus Welander, Diogo Castro, Giuseppe Lo Presti
License: Apache 2.0
Classifier: Development Status :: 4 - Beta
Classifier: License :: OSI Approved :: Apache Software License
Classifier: Programming Language :: Python :: 3
Classifier: Programming Language :: Python :: 3.7
Classifier: Programming Language :: Python :: 3.8
Classifier: Programming Language :: Python :: 3.9
Classifier: Programming Language :: Python :: 3.10
Classifier: Operating System :: OS Independent
License-File: LICENSE
Requires-Dist: grpcio>=1.47.0
Requires-Dist: grpcio-tools>=1.47.0
Requires-Dist: pyOpenSSL
Requires-Dist: requests
Requires-Dist: cs3apis
Requires-Dist: PyJWT
Requires-Dist: protobuf
Requires-Dist: cryptography
Dynamic: author
Dynamic: classifier
Dynamic: description
Dynamic: description-content-type
Dynamic: home-page
Dynamic: license
Dynamic: license-file
Dynamic: requires-dist
Dynamic: summary
